no_pyide/__init__.py
no_pyide/__main__.py
no_pyide/code.py
no_pyide/templates/index.html
no_pyide/templates/results.html
no_pyide-1.0.0.dist-info/LICENSE
no_pyide-1.0.0.dist-info/METADATA
no_pyide-1.0.0.dist-info/WHEEL
no_pyide-1.0.0.dist-info/entry_points.txt
no_pyide-1.0.0.dist-info/top_level.txt
no_pyide-1.0.0.dist-info/RECORD
